s3monkey/__init__.py
s3monkey/__version__.py
s3monkey/core.py
s3monkey/pyfakefs/__init__.py
s3monkey/pyfakefs/deprecator.py
s3monkey/pyfakefs/fake_filesystem.py
s3monkey/pyfakefs/fake_filesystem_shutil.py
s3monkey/pyfakefs/fake_filesystem_unittest.py
s3monkey/pyfakefs/fake_pathlib.py
s3monkey/pyfakefs/fake_scandir.py
s3monkey/pyfakefs/helpers.py
s3monkey/pyfakefs/mox3_stubout.py
s3monkey/pyfakefs/pytest_plugin.py
s3monkey-0.1.1.dist-info/METADATA
s3monkey-0.1.1.dist-info/NOTICE
s3monkey-0.1.1.dist-info/WHEEL
s3monkey-0.1.1.dist-info/top_level.txt
s3monkey-0.1.1.dist-info/RECORD
