Metadata-Version: 2.1
Name: s3monkey
Version: 0.1.1
Summary: A Python library that allows you to interact with Amazon S3 Buckets as if they are your local filesystem.
Home-page: https://github.com/kobayashi/s3monkey
Author: kobayashi
Author-email: abok.1k@gmail.com
License: MIT
Platform: UNKNOWN
Classifier: License :: OSI Approved :: MIT License
Classifier: Programming Language :: Python
Classifier: Programming Language :: Python :: 3
Classifier: Programming Language :: Python :: 3.3
Classifier: Programming Language :: Python :: 3.4
Classifier: Programming Language :: Python :: 3.5
Classifier: Programming Language :: Python :: 3.6
Classifier: Programming Language :: Python :: Implementation :: CPython
Classifier: Programming Language :: Python :: Implementation :: PyPy
Requires-Dist: chardet
Requires-Dist: bucketstore
